<?xml version="1.0" encoding="utf-8"?>
<resources>
    <!-- Missing translations for language: de -->

    <!-- Module: appmanager - 4 strings -->
    <plurals name="dialogs_question_message_template">
        <item quantity="one">Möchten Sie die Raumvorlage «%s» wirklich löschen? Die Vorlage kann nicht wiederhergestellt werden.</item>
                <item quantity="other">Möchten Sie die ausgewählten Raumvorlagen wirklich löschen? Sie können nicht wiederhergestellt werden.</item>
    </plurals>
    <plurals name="dialogs_question_delete_template_title">
        <item quantity="one">Vorlage löschen</item>
                <item quantity="other">Vorlagen löschen</item>
    </plurals>
    <plurals name="access_members_users_title">
        <item quantity="one">%d Benutzer</item>
                <item quantity="other">%d Benutzer</item>
    </plurals>
    <plurals name="access_members_groups_title">
        <item quantity="one">%d Gruppe</item>
                <item quantity="other">%d Gruppen</item>
    </plurals>
</resources>
