<?xml version="1.0" encoding="utf-8"?>
<resources>
    <!-- Missing translations for language: lo -->

    <!-- Module: appmanager - 7 strings -->
    <string name="list_context_remove_from_list">@string/toolbar_menu_main_remove_from_list</string>
    <plurals name="dialogs_question_message_template">
        <item quantity="one">ທ່ານຕ້ອງການລຶບຫ້ອງແມ່ແບບ «%s» ແທ້ໆບໍ? ແມ່ແບບບໍ່ສາມາດກູ້ຄືນໄດ້.</item>
                <item quantity="other">ທ່ານຕ້ອງການລຶບແມ່ແບບຫ້ອງທີ່ເລືອກແທ້ໆບໍ? ພວກມັນບໍ່ສາມາດຟື້ນຟູໄດ້.</item>
    </plurals>
    <plurals name="dialogs_question_delete_template_title">
        <item quantity="one">ລຶບແມ່ແບບ</item>
                <item quantity="other">ລຶບແມ່ແບບ</item>
    </plurals>
    <plurals name="app_settings_passcode_many_attempt_seconds">
        <item quantity="one">ພະຍາຍາມຫຼາຍເກີນໄປ.\nລອງໃໝ່ໃນອີກ %d ວິນາທີ</item>
                <item quantity="other">ພະຍາຍາມຫຼາຍເກີນໄປ.\nລອງໃໝ່ໃນອີກ %d ວິນາທີ</item>
    </plurals>
    <plurals name="app_settings_passcode_many_attempt_minutes">
        <item quantity="one">ພະຍາຍາມຫຼາຍເທື່ອເກີນໄປ.\nລອງໃໝ່ໃນອີກ %d ນາທີ</item>
                <item quantity="other">ພະຍາຍາມຫຼາຍເທື່ອເກີນໄປ.\nລອງໃໝ່ໃນອີກ %d ນາທີ</item>
    </plurals>
    <plurals name="access_members_users_title">
        <item quantity="one">%d ຜູ້ໃຊ້</item>
                <item quantity="other">%d ຜູ້ໃຊ້</item>
    </plurals>
    <plurals name="access_members_groups_title">
        <item quantity="one">%d ກຸ່ມ</item>
                <item quantity="other">%d ກຸ່ມ</item>
    </plurals>

    <!-- Module: libtoolkit - 2 strings -->
    <plurals name="months">
        <item quantity="one">ເດືອນ</item>
                <item quantity="other">ເດືອນ</item>
    </plurals>
    <plurals name="years">
        <item quantity="one">ປີ</item>
                <item quantity="other">ປີ</item>
    </plurals>
</resources>
