<?xml version="1.0" encoding="utf-8"?>
<resources>
    <!-- Missing translations for language: ru -->

    <!-- Module: appmanager - 122 strings -->
    <string name="access_members_me_and_title">Я и %s</string>
    <string name="access_members_me_subtitle">(Я)</string>
    <string name="access_members_me_users_groups_title">Я, %1$s и %2$s</string>
    <string name="cloud_create_account">Создать бесплатную учетную запись</string>
    <string name="context_menu_desc">Больше</string>
    <string name="desc_create_from_template">Создать комнату на основе шаблона. Все настройки, пользователи, папки и файлы будут взяты из выбранного шаблона комнаты.</string>
    <string name="desc_info_template">Шаблон комнаты. Используйте этот шаблон, чтобы быстро создать новую комнату.</string>
    <string name="dialogs_warning_room_space_quota_exceed">Превышена квота пространства в комнате (%s).</string>
    <string name="edit_comment_field_label">Комментарий</string>
    <string name="edit_comment_label">Комментарий</string>
    <string name="edit_comment_success">Комментарий успешно сохранен</string>
    <string name="edit_comment_title">Редактировать комментарий</string>
    <string name="error_create_room">Не удалось создать комнату</string>
    <string name="error_create_template">Не удалось создать шаблон</string>
    <string name="error_edit_comment">Не удалось обновить комментарий</string>
    <string name="error_save_access_settings">Не удалось сохранить настройки доступа</string>
    <string name="error_save_template">Не удалось сохранить шаблон</string>
    <string name="error_upload_logo">Не удалось загрузить логотип</string>
    <string name="error_version_delete">Не удалось удалить</string>
    <string name="error_version_open">Не удалось открыть документ</string>
    <string name="error_version_restore">Не удалось восстановить версию</string>
    <string name="errors_open_document">Не удалось открыть документ</string>
    <string name="errors_webdav_2fa_code">Неправильный код подтверждения</string>
    <string name="filling_form_complete">Завершено</string>
    <string name="filling_form_filling_process_details">Данные процесса</string>
    <string name="filling_form_filling_status">Статус заполнения</string>
    <string name="filling_form_filling_status_desc">На этой панели вы можете следить за заполнением формы, в заполнении которой вы участвуете или в которой вы являетесь организатором заполнения.</string>
    <string name="filling_form_history_complete">Заполнил и отправил свою часть формы. Форма полностью заполнена.</string>
    <string name="filling_form_history_opened">Открыл форму для заполнения</string>
    <string name="filling_form_history_stopped">Заполнение остановлено %s</string>
    <string name="filling_form_history_submitted">Отправил свою часть. Форма была отправлена ​​следующей роли.</string>
    <string name="filling_form_send_finalized">Раздел формы заполнен</string>
    <string name="filling_form_send_finalized_desc">Форма заполнена всеми ролями и завершена. Она доступна в режиме только для просмотра.</string>
    <string name="filling_form_send_section_complete">Раздел формы заполнен</string>
    <string name="filling_form_send_section_complete_desc">Назначенная часть PDF-формы успешно заполнена. Статус заполнения формы можно отслеживать в комнате и через панель «Статус заполнения». Уведомление по электронной почте будет отправлено, как только форма будет полностью заполнена.</string>
    <string name="filling_form_stop_filling">Остановить заполнение</string>
    <string name="filling_form_stop_filling_dialog_desc">Вы уверены, что хотите остановить заполнение? После отмены заполнение этой формы возобновить будет невозможно. Заполнение формы будет остановлено на текущем этапе. Файл будет отмечен как \"Остановлено\".</string>
    <string name="filling_form_stop_filling_dialog_title">Остановить заполнение?</string>
    <string name="filling_form_stopped">Остановлено</string>
    <string name="filling_form_version_incompatible_desc">Версии клиента и сервера несовместимы. Документ можно открыть только в режиме просмотра.</string>
    <string name="filter_type_pdf_documents">PDF-документы</string>
    <string name="filter_type_pdf_forms">PDF-формы</string>
    <string name="form_status_complete">Заполнено</string>
    <string name="form_status_draft">Черновик</string>
    <string name="form_status_in_progress">В процессе</string>
    <string name="form_status_stopped">Остановлено</string>
    <string name="form_status_your_turn">Ваша очередь</string>
    <string name="fragment_templates_title">Шаблоны</string>
    <string name="list_action_doc_from_photo">Текстовый документ из фотографии</string>
    <string name="list_context_access_settings">Настройки доступа</string>
    <string name="list_context_delete_template">Удалить шаблон</string>
    <string name="list_context_disable_custom_filter">Отключить пользовательский фильтр</string>
    <string name="list_context_edit_comment">Редактировать комментарий</string>
    <string name="list_context_edit_index">Редактировать индекс</string>
    <string name="list_context_edit_template">Редактировать шаблон</string>
    <string name="list_context_enable_custom_filter">Включить пользовательский фильтр</string>
    <string name="list_context_lock">Заблокировать</string>
    <string name="list_context_open_vesrion">Открыть</string>
    <string name="list_context_save_as_template">Сохранить как шаблон</string>
    <string name="list_context_unlock">Разблокировать</string>
    <string name="list_context_upload_to_cloud">Загрузить в облако</string>
    <string name="list_context_version_history">Показать историю версий</string>
    <string name="on_boarding_collaborate_header">Работайте вместе с командой</string>
    <string name="on_boarding_collaborate_info">
В онлайн режиме используйте функциональные возможности ONLYOFFICE для совместного редактирования в реальном времени для работы над документами вместе с участниками вашего портала, обмена документами и создания общих папок для хранения.
    </string>
    <string name="on_boarding_edit_header">Работайте с офисными файлами</string>
    <string name="on_boarding_edit_info">
        Создавайте и редактируйте документы с помощью панели инструментов: работайте со сложными объектами в текстовых документах, выполняйте сложные вычисления в электронных таблицах, создавайте впечатляющие презентации и просматривайте PDF-файлы без потери форматирования.
    </string>
    <string name="on_boarding_finish_button">Начать</string>
    <string name="on_boarding_locally_header">Редактируйте документы локально</string>
    <string name="on_boarding_locally_info">
        Работайте с документами офлайн. Созданные файлы впоследствии можно загрузить на онлайн портал и получить к ним доступ с любого другого устройства.
    </string>
    <string name="on_boarding_third_party_header">Стороннее хранилище</string>
    <string name="on_boarding_third_party_info">
        Подключите сторонние хранилища, такие как Nextcloud, ownCloud, Dropbox и другие, которые используют протокол WebDAV.
    </string>
    <string name="on_boarding_welcome_header">Начало работы</string>
    <string name="on_boarding_welcome_info">
      Добро пожаловать в мобильные редакторы ONLYOFFICE! Проведите по экрану, чтобы узнать больше о приложении.
    </string>
    <string name="operation_disable_custom_filter">Пользовательский фильтр для выбранного файла отключен</string>
    <string name="operation_enable_custom_filter">Пользовательский фильтр для выбранного файла включен</string>
    <string name="placeholder_connection_button">Перезагрузить</string>
    <string name="placeholder_connection_desc">Соединение не обнаружено. Проверьте соединение и попробуйте еще раз.</string>
    <string name="placeholder_empty_templates_folder">Шаблонов пока нет</string>
    <string name="placeholder_empty_templates_folder_desc">Вы можете создать шаблон из комнаты в разделе «Комната».</string>
    <string name="room_access_via_link_title">Доступ по ссылке</string>
    <string name="room_created_successfully">Комната успешно создана</string>
    <string name="room_placeholder_created_template_title">Шаблон создан!</string>
    <string name="setting_access_desc">Доступ к шаблону. Вы можете выбрать участников, которые могут создавать комнаты на основе этого шаблона.</string>
    <string name="setting_access_list_title">Доступ к шаблону</string>
    <string name="setting_access_members_title">Добавить пользователей или группы</string>
    <string name="setting_access_members_title_desc">Добавленные администраторы смогут создавать комнаты, используя этот шаблон.</string>
    <string name="setting_access_public">Шаблон доступен каждому</string>
    <string name="setting_access_public_bold_docspace">DocSpace</string>
    <string name="setting_access_public_bold_room">Администраторы комнат</string>
    <string name="setting_access_public_desc">Все администраторы DocSpace и комнат смогут создавать комнаты, используя этот шаблон.</string>
    <string name="setting_screen_on">При просмотре документов</string>
    <string name="setting_select_members_title">Выбрать участников</string>
    <string name="setting_tags_desc">Теги применяются к комнате, которая будет создана на основе этого шаблона.</string>
    <string name="setting_title_sreen_on">Оставить экран включенным</string>
    <string name="settings_saved_successfully">Настройки шаблона сохранены</string>
    <string name="share_clipboard_external_custom_filter_copied">Ссылка на файл с включенным Пользовательским фильтром успешно скопирована в буфер обмена.</string>
    <string name="share_user_type_room_portal_owner">Владелец портала</string>
    <string name="share_user_type_room_workspace_owner">Владелец рабочего пространства</string>
    <string name="template_created_successfully">Шаблон «%s» сохранен</string>
    <string name="template_delete_success">Шаблон удален</string>
    <string name="template_name_hint">Имя шаблона</string>
    <string name="template_subheader_title">Шаблон комнаты</string>
    <string name="templates_delete_success">Шаблоны удалены</string>
    <string name="title_access_settings">Настройки доступа</string>
    <string name="title_create_from_template">Из шаблона</string>
    <string name="title_edit_template">Редактировать шаблон</string>
    <string name="title_save_template">Сохранить как шаблон</string>
    <string name="version_delete_confirm">Удалить</string>
    <string name="version_delete_done">Версия удалена</string>
    <string name="version_delete_loading">Удаление</string>
    <string name="version_delete_subtitle">Вы собираетесь удалить версию файла. Ее невозможно будет увидеть или восстановить. Продолжить?</string>
    <string name="version_delete_title">Удалить версию</string>
    <string name="version_dialog_cancel">Отменить</string>
    <string name="version_edit_comment_title">Редактировать комментарий</string>
    <string name="version_group_current_header">Текущая — Версия %s</string>
    <string name="version_group_header">Версия %s</string>
    <string name="version_history_title">История версий</string>
    <string name="version_restore_confirm">Восстановить</string>
    <string name="version_restore_done">Версия восстановлена</string>
    <string name="version_restore_loading">Восстановление версии</string>
    <string name="version_restore_subtitle">Текущий файл будет сохранен в истории версий.</string>
    <string name="version_restore_title">Восстановить эту версию?</string>

  <!-- Module: libgdocs - 1 strings -->
    <string name="review_line_spacing">@string/settings_line_spacing</string>

    <!-- Module: libgeditors - 12 strings -->
    <string name="comment_error">Ошибка при изменении комментария</string>
    <string name="dialog_recognizing_title">Распознавание текста…</string>
    <string name="error_protection_edit">Вы не можете редактировать этот фрагмент, так как он защищен.</string>
    <string name="pdf_reader_error_password_version">Эта версия Android не поддерживает защищенные паролем PDF-файлы, используйте другое приложение.</string>
    <string name="recognize_empty">На изображении не обнаружено текста для распознавания</string>
    <string name="recognize_error">Ошибка при распознавании</string>
    <string name="scan_document_title">Сканировать документ</string>
    <string name="settings_draw_brush">Кисть</string>
    <string name="settings_line_size_title">Размер линии</string>
    <string name="take_gallery_image">Из галереи</string>
    <string name="take_photo">Из фотографии</string>
    <string name="take_photo_error">Не удалось загрузить изображение</string>

  <!-- Module: libtoolkit - 4 strings -->
    <string name="help_and_feedback_contact_support">Связаться со службой поддержки</string>
    <string name="help_and_feedback_help_center">Справочный центр</string>
    <string name="help_and_feedback_suggest_a_feature">Предложить функцию</string>
    <string name="help_and_feedback_title">Помощь и обратная связь</string>
</resources>
